cybertemp/__init__.py
cybertemp/cybertemp.py
cybertemp-0.1.2.dist-info/licenses/LICENSE
cybertemp-0.1.2.dist-info/METADATA
cybertemp-0.1.2.dist-info/WHEEL
cybertemp-0.1.2.dist-info/top_level.txt
cybertemp-0.1.2.dist-info/RECORD
