Metadata-Version: 2.4
Name: cybertemp
Version: 0.1.2
Summary: A Python wrapper for the CyberTemp temporary email service API
Home-page: https://github.com/sexfrance/cybertemp-wrapper
Author: Sexfrance
Author-email: bwuuuuu@gmail.com
Project-URL: Documentation, https://cybertemp.xyz/api-docs
Project-URL: Source, https://github.com/sexfrance/cybertemp-wrapper
Project-URL: Issues, https://github.com/sexfrance/cybertemp-wrapper/issues
Keywords: email,temporary-email,disposable-email,api-wrapper,cybertemp
Classifier: Programming Language :: Python :: 3.8
Classifier: Programming Language :: Python :: 3.9
Classifier: Programming Language :: Python :: 3.10
Classifier: Programming Language :: Python :: 3.11
Classifier: Development Status :: 4 - Beta
Classifier: Intended Audience :: Developers
Classifier: License :: OSI Approved :: MIT License
Classifier: Operating System :: OS Independent
Classifier: Topic :: Communications :: Email
Classifier: Topic :: Software Development :: Libraries :: Python Modules
Requires-Python: >=3.8
License-File: LICENSE
Requires-Dist: logmagix
Requires-Dist: requests
Dynamic: author
Dynamic: author-email
Dynamic: classifier
Dynamic: description
Dynamic: description-content-type
Dynamic: home-page
Dynamic: keywords
Dynamic: license-file
Dynamic: project-url
Dynamic: requires-dist
Dynamic: requires-python
Dynamic: summary
